sceptre_s3_packager/__init__.py
sceptre_s3_packager/s3_packager.py
sceptre_s3_packager-0.4.0.dist-info/LICENSE
sceptre_s3_packager-0.4.0.dist-info/METADATA
sceptre_s3_packager-0.4.0.dist-info/WHEEL
sceptre_s3_packager-0.4.0.dist-info/entry_points.txt
sceptre_s3_packager-0.4.0.dist-info/top_level.txt
sceptre_s3_packager-0.4.0.dist-info/RECORD
