Metadata-Version: 2.1
Name: sceptre-s3-packager
Version: 0.4.0
Summary: S3 packager for Sceptre 2
Home-page: https://github.com/henrist/sceptre-s3-packager
Author: Henrik Steen
Classifier: Development Status :: 4 - Beta
Classifier: Programming Language :: Python :: 3
Classifier: License :: OSI Approved :: MIT License
License-File: LICENSE
Requires-Dist: sceptre (>=2)
